<?xml version="1.0" encoding="utf-8"?>

<ArrayOfNewsData> 
    <NewsData> 
        <NewsMarks>省一级|特稿与特写|留守儿童犯罪等|企业|问题儿童|设立长期资助项目|公益团体|事业单位|私立学校教学质量没保障|男</NewsMarks>  
        <Date>2015</Date>  
        <ID>news:050k^201512283121327(S:196124888)</ID> 
    </NewsData>  
    <NewsData> 
        <NewsMarks>中央一级|纯净新闻|表彰帮助关爱留守儿童的单位或个人|记者|积极健康|单纯一次捐款捐物|事业单位|政府部门|无本地户籍难入公立学校|男</NewsMarks>  
        <Date>2015</Date>  
        <ID>news:03eg^201512283121325(S:196124888)</ID> 
    </NewsData>  
    <NewsData> 
        <NewsMarks>经营模式市场化|评论|社会各界帮助关爱|记者|积极健康|单纯一次捐款捐物|政府部门|政府部门|无本地户籍难入公立学校|男</NewsMarks>  
        <Date>2010</Date>  
        <ID>news:1862^201012285331759(S:193625388)</ID> 
    </NewsData> 
</ArrayOfNewsData>
